HISTORY.rst
LICENSE.rst
MANIFEST.in
README.rst
setup.py
src/collective/__init__.py
src/collective.pfg.soup.egg-info/PKG-INFO
src/collective.pfg.soup.egg-info/SOURCES.txt
src/collective.pfg.soup.egg-info/dependency_links.txt
src/collective.pfg.soup.egg-info/entry_points.txt
src/collective.pfg.soup.egg-info/namespace_packages.txt
src/collective.pfg.soup.egg-info/requires.txt
src/collective.pfg.soup.egg-info/top_level.txt
src/collective.pfg.soup.egg-info/zip-safe
src/collective/pfg/__init__.py
src/collective/pfg/soup/__init__.py
src/collective/pfg/soup/adapter.py
src/collective/pfg/soup/config.py
src/collective/pfg/soup/configure.zcml
src/collective/pfg/soup/extender.py
src/collective/pfg/soup/indexadapters.py
src/collective/pfg/soup/interfaces.py
src/collective/pfg/soup/storage.py
src/collective/pfg/soup/subscribers.py
src/collective/pfg/soup/browser/__init__.py
src/collective/pfg/soup/browser/action.py
src/collective/pfg/soup/browser/configure.zcml
src/collective/pfg/soup/browser/edit.py
src/collective/pfg/soup/browser/export.py
src/collective/pfg/soup/browser/log.pt
src/collective/pfg/soup/browser/log.py
src/collective/pfg/soup/browser/remove.py
src/collective/pfg/soup/browser/table.pt
src/collective/pfg/soup/browser/table.py
src/collective/pfg/soup/browser/utils.py
src/collective/pfg/soup/browser/resources/table.js
src/collective/pfg/soup/profile/browserlayer.xml
src/collective/pfg/soup/profile/factorytool.xml
src/collective/pfg/soup/profile/jsregistry.xml
src/collective/pfg/soup/profile/metadata.xml
src/collective/pfg/soup/profile/rolemap.xml
src/collective/pfg/soup/profile/types.xml
src/collective/pfg/soup/profile/workflows.xml
src/collective/pfg/soup/profile/types/FormFolder.xml
src/collective/pfg/soup/profile/types/SoupAdapter.xml