Metadata-Version: 1.1
Name: collective.pfg.soup
Version: 1.2
Summary: PloneFormGen Action Adapter: store, show/search, edit, csv-export, based on souper.soup
Home-page: https://pypi.python.org/pypi/collective.pfg.soup
Author: BlueDynamics Alliance
Author-email: dev@bluedynamics.com
License: GPLv2
Platform: UNKNOWN
Classifier: Development Status :: 5 - Production/Stable
Classifier: License :: OSI Approved :: GNU General Public License (GPL)
Classifier: Operating System :: OS Independent
Classifier: Programming Language :: Python
Classifier: Topic :: Software Development
Classifier: Framework :: Plone
